{
  "menus": [
    {
      "weekStart": "2026-04-06",
      "weekEnd": "2026-04-12",
      "file": "data/menus/2026-04-06.json",
      "label": "Semaine du 6 avril 2026",
      "healthScore": "A",
      "highlights": [
        "3 poissons sûrs · Zéro maquereau cette semaine",
        "Pâtes bolognaises mercredi — le plat préféré des enfants",
        "20 plats de saison sur 28 🌸",
        "Gigot d'agneau de lait dominical"
      ]
    },
    {
      "weekStart": "2026-03-30",
      "weekEnd": "2026-04-05",
      "file": "data/menus/2026-03-30.json",
      "label": "Semaine du 30 mars 2026",
      "healthScore": "A",
      "highlights": [
        "Saumon vapeur & quinoa",
        "Cabillaud en papillote",
        "5 légumineuses cette semaine",
        "Gigot d'agneau dominical"
      ]
    }
  ]
}
